{
  "module_id": "100",
  "title": "ونفس 72 | مجلس مفتوح لإجابة الأسئلة",
  "subtitle": "أهداف التعلم",
  "objectives": [
    "تطبيق \"فقه الأولى والبيان\" في التعامل مع الأخطاء المجتمعية الشائعة.",
    "تحليل مهارة \"مداراة الناس\" دون الوقوع في المداهنة المحرمة.",
    "تحديد ضوابط \"الأمر بالمعروف والنهي عن المنكر\" في المجالس العائلية.",
    "تقييم مخاطر \"ترخيص الدين\" في الوسائل الإعلامية المعاصرة.",
    "تحليل مفهوم \"رغبة الجنة\" وعلاقتها بالإخلاص والدافعية البشرية.",
    "استنتاج أهمية \"فقه الصمت\" في بناء الخلوات الروحية اليومية.",
    "تحليل كيفية التعامل مع \"الكبر الخفي\" الناتج عن التميز الأخلاقي.",
    "تحديد أثر \"الصدق\" في إصلاح العلاقات الزوجية والاجتماعية المضطربة."
  ],
  "concepts": [],
  "sections": [],
  "key_points": [
    "التي يجب تذكرها",
    "الحكمة هي بوصلة \"الغريب\"؛ فاعرف متى تنكر بيدك، ومتى بلسانك، ومتى بقلبك وهو أضعف الإيمان.",
    "رغبة الجنة هي وقود العبودية الصادقة؛ فلا تدع الفلسفات الباردة تطفئ شوقك لنعيم الله.",
    "رخص الدين يقتله في القلوب؛ فصن مبادئك من أن توضع في سياقات الابتذال.",
    "التنافس الحقيقي هو مع \"نفسك الأمس\"؛ فاجعل مضمارك لله ولا تلتفت لضجيج المنافسين.",
    "الصمت عند الأذان هو \"تدريب أركان\" على الإخلاص والتعظيم قبل الدخول في الصلاة.",
    "بر الوالدين هو الجهاد الأكبر؛ فاجعل من إزعاجهم لك مختبراً للصبر وطلب الأجر."
  ],
  "practical_applications": [
    "في أول اجتماع عائلي، مارس \"الصمت الحكيم\"؛ لا تهاجم أحداً، فقط ابقَ هادئاً وابتسم للحق وأعرض عن اللغو.",
    "إذا عزمت على ترك عادة سيئة، لا تخبر أحداً؛ اجعلها \"خبيئة\" بينك وبين الله واطلب منه الثبات.",
    "تدرب على \"ضعفاء في الباطل\"؛ إذا أتيحت لك فرصة غيبة أو سخرية، فادعُ الله فوراً أن يخرس لسانك.",
    "اجعل لنفسك \"مضماراً\" خاصاً اليوم؛ حدد هدفاً (مثل ختم جزء أو صلة رحم) وأتمه دون أن تنظر لمن أنجز أكثر منك.",
    "عند رؤية منكر لا تستطيع تغييره، قل في نفسك: \"اللهم إن هذا منكر لا يرضيك\"، وانصرف بهدوء وصيانة لقلبك.",
    "خصص 5 دقائق بعد صلاة الفجر للصمت التام وتخيل \"الجائزة\" (الجنة) لتستقبل يومك بروح قوية ومتفائلة.",
    "الوثيقة 17 من."
  ],
  "metadata": {
    "created_date": "2026-04-02",
    "version": "1.0",
    "language": "ar",
    "difficulty_level": "intermediate",
    "word_count": 1107
  }
}