{
  "module_id": "124",
  "title": "ونفس 96 | خلاصات المجالس السابقة",
  "subtitle": "أهداف التعلم",
  "objectives": [
    "تلخيص هيكلية \"منهاج فقه النفس\" من خلال الثلاثية (اقرأ، ونفس، لتعارفوا).",
    "تحديد معالم \"تاريخ النفس\" وأثره في تشكيل المدخلات المعاصرة.",
    "التمييز بين مراحل المعالجة النفسية (الحس، التفكير، العقل).",
    "تحليل معوقات العقل والنجاة المتمثلة في (صمم) و (الجهل والهوى والآفات).",
    "استنباط مفهوم \"العقل في القرآن\" وعلاقته بالتأديب والعمل.",
    "تطبيق منهجية (عقل، وحي، نظر) للوصول للحقيقة والحق.",
    "استنتاج معالم \"المخلوقية\" وسننها النفسية والروحية.",
    "تحديد متطلبات الانتقال لمرحلة \"لتعارفوا\" من خلال فقه الأخلاق."
  ],
  "concepts": [],
  "sections": [],
  "key_points": [
    "التي يجب تذكرها"
  ],
  "practical_applications": [],
  "metadata": {
    "created_date": "2026-04-02",
    "version": "1.0",
    "language": "ar",
    "difficulty_level": "intermediate",
    "word_count": 884
  }
}