{
  "module_id": "054",
  "title": "ونفس 26 | فقه الألم 04 | ثمرات الألم ونِعمه 01",
  "subtitle": "أهداف التعلم",
  "objectives": [
    "التمييز بين \"الثقة بالله\" و\"الثقة بالنفس\" من منظور فقه النفس الإسلامي.",
    "تحليل قصيدة \"طبعت على كدر\" لاستنباط حقيقة الدنيا بكونها دار كد وألم.",
    "شرح أثر \"الترك\" كمتطلب أساسي لعملية \"التركيز\" الذهني والنفسي.",
    "استنتاج العلاقة بين تكرار \"الحاجات\" وتكرار \"الآلام\" كقاعدة كونية.",
    "تحليل \"صوارف الهوى\" (الكبر، الكذب، الكسل) التي تمنع النفس من رؤية ثمرات الألم.",
    "شرح كيفية تحقيق \"العبودية\" و\"التسليم\" من خلال تجربة الانكسار تحت وطأة الألم.",
    "تحليل فلسفة \"الخوف والرجاء\" كمحركين نفسيين نابعين من تجربة الألم.",
    "استنباط الحكمة من \"العذاب الأدنى\" كبوابة للرجوع إلى الله (لعلهم يرجعون)."
  ],
  "concepts": [],
  "sections": [],
  "key_points": [
    "التي يجب تذكرها",
    "الدنيا مجبولة على الكدر، ومحاولة تصفيتها من الألم هي معاندة لسنن الخلق تزيد من شقاء النفس.",
    "الثبات النفسي يبدأ من \"الثقة بالله\" لا \"الثقة بالنفس\"، فالألم يكسر النفس ليقوي الصلة بالله.",
    "التركيز يتطلب \"تركاً\"؛ فصبرك على ألم ترك المشتتات واللذات العابرة هو وقود نجاحك الحقيقي.",
    "الألم هو \"المطهر\" الذي يخلص النفس من خبث الكبر والادعاء، كما يخلص الكير خبث الحديد.",
    "الخوف والرجاء لا يتحققان بلا ألم؛ فالألم يولد الخوف من بقائه والرجاء في زواله عند الخالق.",
    "كل بلاء يصيب المؤمن (وصب، نصب، هم) هو عملية تنقية ورفع درجات لا تضيع سدى عند الله."
  ],
  "practical_applications": [
    "عندما تفشل في أمر ما، لا تلم \"ظروفك\" بل استعمل الألم كبصيرة لمراجعة صدقك وقوة سعيك.",
    "درب نفسك على \"سنة الترك\"؛ اترك هاتفك لساعة يومياً وصابر على ألم \"الفضول\" لتزيد من تركيزك.",
    "إذا أصبت بمرض أو تعب، استشعر فوراً معنى \"تكفير الخطايا\" وحوّل وجعك إلى عبادة صبر صامتة.",
    "توقف عن قراءة الروايات الهروبية التي تزيد من \"وهن الروح\"، واجه واقعك بشجاعة المبتلى المحتسب.",
    "عند رؤية نعم الآخرين، تذكر أن \"الترف مفسدة\"، واشكر الله على آلامك التي أبقتك منكسراً لبابه.",
    "قل لنفسك عند كل ضيق: \"هذه هي الدنيا\"، لتمتص صدمة الألم وتمنعها من التحول إلى سخط على القدر."
  ],
  "metadata": {
    "created_date": "2026-04-02",
    "version": "1.0",
    "language": "ar",
    "difficulty_level": "intermediate",
    "word_count": 1024
  }
}